elasticsearch_query_builder/__init__.py
elasticsearch_query_builder/builders.py
elasticsearch_query_builder/fields/__init__.py
elasticsearch_query_builder/fields/abstract.py
elasticsearch_query_builder/fields/choice.py
elasticsearch_query_builder/fields/exists.py
elasticsearch_query_builder/fields/ids.py
elasticsearch_query_builder/fields/match.py
elasticsearch_query_builder/fields/match_bool_prefix.py
elasticsearch_query_builder/fields/match_phrase.py
elasticsearch_query_builder/fields/match_phrase_prefix.py
elasticsearch_query_builder/fields/multi_match.py
elasticsearch_query_builder/fields/nested.py
elasticsearch_query_builder/fields/query_string.py
elasticsearch_query_builder/fields/range.py
elasticsearch_query_builder/fields/term.py
elasticsearch_query_builder/fields/terms.py
elasticsearch_query_builder-0.1.dist-info/LICENSE
elasticsearch_query_builder-0.1.dist-info/METADATA
elasticsearch_query_builder-0.1.dist-info/WHEEL
elasticsearch_query_builder-0.1.dist-info/top_level.txt
elasticsearch_query_builder-0.1.dist-info/RECORD
