Metadata-Version: 2.1
Name: elasticsearch-query-builder
Version: 0.1
Summary: A tool for forming a single query body for further search in Elasticsearch
Home-page: https://github.com/kirillpechurin/elasticsearch-query-builder
Author: kirillpechurin
Author-email: k.pechurin04@gmail.com
Project-URL: Repository, https://github.com/kirillpechurin/elasticsearch-query-builder
Classifier: Development Status :: 2 - Pre-Alpha
Classifier: License :: OSI Approved :: Apache Software License
Classifier: Natural Language :: English
Classifier: Programming Language :: Python :: 3
Classifier: Programming Language :: Python :: 3.8
Classifier: Programming Language :: Python :: 3.9
Classifier: Programming Language :: Python :: 3.10
Classifier: Programming Language :: Python :: 3.11
Requires-Python: >=3.8
License-File: LICENSE
